sanic_beskar/__init__.py
sanic_beskar/base.py
sanic_beskar/constants.py
sanic_beskar/decorators.py
sanic_beskar/exceptions.py
sanic_beskar/orm/__init__.py
sanic_beskar/orm/beanie_user_mixins.py
sanic_beskar/orm/tortoise_user_mixins.py
sanic_beskar/orm/umongo_user_mixins.py
sanic_beskar/py.typed
sanic_beskar/templates/registration_email.html
sanic_beskar/templates/reset_email.html
sanic_beskar/utilities.py
sanic_beskar-2.3.4.post1.dist-info/LICENSE.rst
sanic_beskar-2.3.4.post1.dist-info/METADATA
sanic_beskar-2.3.4.post1.dist-info/WHEEL
sanic_beskar-2.3.4.post1.dist-info/RECORD
