Metadata-Version: 2.1
Name: sanic-beskar
Version: 2.3.4.post1
Summary: Strong, Simple, (now async!) and Precise security for Sanic APIs
Home-page: https://sanic-beskar.readthedocs.io/en/latest/
License: MIT
Author: Rob Dailey
Author-email: rob@suspected.org
Requires-Python: >=3.9,<4.0
Classifier: License :: OSI Approved :: MIT License
Classifier: Programming Language :: Python :: 3
Classifier: Programming Language :: Python :: 3.9
Classifier: Programming Language :: Python :: 3.10
Classifier: Programming Language :: Python :: 3.11
Classifier: Programming Language :: Python :: 3.12
Requires-Dist: cryptography (>=39.0.0)
Requires-Dist: jinja2 (>=3.1.2)
Requires-Dist: passlib (>=1.7)
Requires-Dist: pendulum (==3.0.*) ; python_version >= "3.12"
Requires-Dist: pendulum (>=2.1,<3.0) ; python_version >= "3.9" and python_version < "3.12"
Requires-Dist: py-buzz (>3.2.0)
Requires-Dist: pyjwt (>=2.6)
Requires-Dist: pyseto (>=1.6.9)
Requires-Dist: sanic (>=22.6.0)
Project-URL: Documentation, https://sanic-beskar.readthedocs.io/en/latest/
Project-URL: Repository, https://github.com/pahrohfit/sanic-beskar
